intra_search/__init__.py
intra_search/cli.py
intra_search/config.py
intra_search/doc.py
intra_search/model.py
intra_search/server.py
intra_search/store.py
intra_search/utils.py
ui/dist/index.html
ui/dist/intra-search.svg
ui/dist/assets/__vite-browser-external-BIHI7g3E.js
ui/dist/assets/cursor-editorTextHighlight-kG3uUOwL.svg
ui/dist/assets/index-B6gkhsHn.js
ui/dist/assets/index-BiAfLMSs.js
ui/dist/assets/index-QBeaW7QG.css
ui/dist/assets/pdf_viewer-BDtZ6JaA.js
intra_search-0.1.0.dist-info/METADATA
intra_search-0.1.0.dist-info/WHEEL
intra_search-0.1.0.dist-info/entry_points.txt
intra_search-0.1.0.dist-info/top_level.txt
intra_search-0.1.0.dist-info/RECORD
