Metadata-Version: 2.1
Name: intra-search
Version: 0.1.0
Summary: A tool for performing semantic search within documents using sentence transformers to find contextually relevant text.
Author: Monish Prabhu
Author-email: monish.prabhu.official@gmail.com
License: MIT license
Classifier: Programming Language :: Python :: 3.11
Classifier: License :: OSI Approved :: MIT License
Classifier: Operating System :: OS Independent
Requires-Dist: Flask ==3.0.3
Requires-Dist: Flask-Cors ==4.0.1
Requires-Dist: platformdirs ==4.2.2
Requires-Dist: PyMuPDF ==1.24.9
Requires-Dist: sentence-transformers ==3.0.1
Requires-Dist: tabulate ==0.9.0
Requires-Dist: tqdm ==4.66.4
